environment_variables/__init__.py
environment_variables/classes.py
environment_variables/exceptions.py
environment_variables/variables.py
environment_variables-0.1.0.dist-info/AUTHORS
environment_variables-0.1.0.dist-info/LICENSE
environment_variables-0.1.0.dist-info/METADATA
environment_variables-0.1.0.dist-info/WHEEL
environment_variables-0.1.0.dist-info/pbr.json
environment_variables-0.1.0.dist-info/top_level.txt
environment_variables-0.1.0.dist-info/RECORD
