Metadata-Version: 2.1
Name: environment-variables
Version: 0.1.0
Summary: Load environment variables Enum style
Home-page: https://github.com/jtaxen/environment_variables
Author: Jacob Taxén
License: UNKNOWN
Platform: UNKNOWN
Classifier: Programming Language :: Python :: 3
Classifier: License :: OSI Approved :: MIT License
Classifier: Operating System :: OS Independent
Requires-Python: >=3.7
License-File: LICENSE
License-File: AUTHORS
